{
  "groups": [
    {
      "name": "ifx.client.netty",
      "type": "com.ifx.connect.properties.ServerNettyConfigProperties",
      "sourceType": "com.ifx.connect.properties.ServerNettyConfigProperties",
      "sourceMethod": "getPort()"
    },
    {
      "name": "ifx.connect.netty.client",
      "type": "com.ifx.connect.properties.ClientNettyConfigProperties",
      "sourceType": "com.ifx.connect.properties.ClientNettyConfigProperties"
    },
    {
      "name": "ifx.connect.netty.server",
      "type": "com.ifx.connect.properties.ServerNettyConfigProperties",
      "sourceType": "com.ifx.connect.properties.ServerNettyConfigProperties"
    },
    {
      "name": "ifx.server.netty",
      "type": "com.ifx.connect.properties.ClientNettyConfigProperties",
      "sourceType": "com.ifx.connect.properties.ClientNettyConfigProperties"
    }
  ],
  "properties": [
    {
      "name": "ifx.connect.client.connectTimeOut",
      "type": "java.lang.Integer",
      "description": "connect timeout ; after the point time , if server has no responese ,connect channel will disConnect",
      "sourceType": "com.ifx.connect.properties.ClientNettyConfigProperties"
    },
    {
      "name": "ifx.connect.client.serverHost",
      "type": "java.lang.String",
      "description": "server deploy host such as  127.0.0.0.1  and  default is same",
      "sourceType": "com.ifx.connect.properties.ClientNettyConfigProperties"
    },
    {
      "name": "ifx.connect.client.serverPort",
      "type": "java.lang.Integer",
      "sourceType": "com.ifx.connect.properties.ClientNettyConfigProperties"
    },
    {
      "name": "ifx.connect.netty.client.auto-re-connect",
      "type": "java.lang.Boolean",
      "sourceType": "com.ifx.connect.properties.ClientNettyConfigProperties"
    },
    {
      "name": "ifx.connect.netty.client.connect-time-out",
      "type": "java.lang.Integer",
      "sourceType": "com.ifx.connect.properties.ClientNettyConfigProperties"
    },
    {
      "name": "ifx.connect.netty.client.retry-times",
      "type": "java.lang.Integer",
      "sourceType": "com.ifx.connect.properties.ClientNettyConfigProperties"
    },
    {
      "name": "ifx.connect.netty.client.server-host",
      "type": "java.lang.String",
      "sourceType": "com.ifx.connect.properties.ClientNettyConfigProperties"
    },
    {
      "name": "ifx.connect.netty.client.server-port",
      "type": "java.lang.Integer",
      "sourceType": "com.ifx.connect.properties.ClientNettyConfigProperties"
    },
    {
      "name": "ifx.connect.netty.server.core-active-socket",
      "type": "java.lang.Integer",
      "sourceType": "com.ifx.connect.properties.ServerNettyConfigProperties"
    },
    {
      "name": "ifx.connect.netty.server.host",
      "type": "java.lang.String",
      "sourceType": "com.ifx.connect.properties.ServerNettyConfigProperties"
    },
    {
      "name": "ifx.connect.netty.server.max-active-socket",
      "type": "java.lang.Integer",
      "sourceType": "com.ifx.connect.properties.ServerNettyConfigProperties"
    },
    {
      "name": "ifx.connect.netty.server.max-time-out",
      "type": "java.lang.Integer",
      "sourceType": "com.ifx.connect.properties.ServerNettyConfigProperties"
    },
    {
      "name": "ifx.connect.netty.server.port",
      "type": "java.lang.Integer",
      "sourceType": "com.ifx.connect.properties.ServerNettyConfigProperties"
    },
    {
      "name": "ifx.connect.server.host",
      "type": "java.lang.String",
      "sourceType": "com.ifx.connect.properties.ServerNettyConfigProperties"
    },
    {
      "name": "ifx.connect.server.port",
      "type": "java.lang.Integer",
      "description": "Description for ifx.connect.socket.",
      "sourceType": "com.ifx.connect.properties.ServerNettyConfigProperties"
    },
    {
      "name": "ifx.connect.socket.port",
      "type": "java.lang.Integer",
      "description": "server deploy port  default port is 10305"
    }
  ],
  "hints": []
}